Metadata-Version: 2.1
Name: gardiner2unicode
Version: 0.0.2
Summary: Mapping Gardiner's codes to Unicode + generating corresponding images.
Home-page: https://github.com/alexeyev/gardiner2unicode
Author: Anton Alekseev
Author-email: anton.m.alexeye@gmail.com
License: UNKNOWN
Keywords: egyptology,ancient egypt,fonts
Platform: UNKNOWN
Classifier: Programming Language :: Python :: 3
Classifier: License :: OSI Approved :: MIT License
Classifier: Operating System :: OS Independent
Requires-Python: >=3.6
